{
  "main": {
    "id": "56bf2cf6fbd947d1",
    "type": "split",
    "children": [
      {
        "id": "72a56d956aa9d5c0",
        "type": "tabs",
        "children": [
          {
            "id": "e520ba2e4beb7d0a",
            "type": "leaf",
            "state": {
              "type": "markdown",
              "state": {
                "file": "Textbooks/Undergraduate/Second Year/Topology Dugundji/Exercises/11. Zorn´s Lemma; Zermelo´s Theorem.md",
                "mode": "source",
                "source": false
              }
            }
          }
        ]
      }
    ],
    "direction": "vertical"
  },
  "left": {
    "id": "64cfd8b1dbbf95e0",
    "type": "mobile-drawer",
    "children": [
      {
        "id": "08eaea14727742f6",
        "type": "leaf",
        "state": {
          "type": "file-explorer",
          "state": {
            "sortOrder": "alphabetical"
          }
        }
      },
      {
        "id": "025100234c011739",
        "type": "leaf",
        "state": {
          "type": "search",
          "state": {
            "query": "",
            "matchingCase": false,
            "explainSearch": false,
            "collapseAll": false,
            "extraContext": false,
            "sortOrder": "alphabetical"
          }
        }
      },
      {
        "id": "06ea433023fcda14",
        "type": "leaf",
        "state": {
          "type": "tag",
          "state": {
            "sortOrder": "frequency",
            "useHierarchy": true
          }
        }
      },
      {
        "id": "7b92d4a6ba55e415",
        "type": "leaf",
        "state": {
          "type": "bookmarks",
          "state": {}
        }
      }
    ],
    "currentTab": 0
  },
  "right": {
    "id": "03ac6a18a1566b7c",
    "type": "mobile-drawer",
    "children": [
      {
        "id": "9a1b208edf12ea5e",
        "type": "leaf",
        "state": {
          "type": "backlink",
          "state": {
            "file": "Textbooks/Undergraduate/Second Year/Topology Dugundji/Exercises/11. Zorn´s Lemma; Zermelo´s Theorem.md",
            "collapseAll": false,
            "extraContext": false,
            "sortOrder": "alphabetical",
            "showSearch": false,
            "searchQuery": "",
            "backlinkCollapsed": false,
            "unlinkedCollapsed": true
          }
        }
      },
      {
        "id": "6cb553aa779f1658",
        "type": "leaf",
        "state": {
          "type": "outgoing-link",
          "state": {
            "file": "Textbooks/Undergraduate/Second Year/Topology Dugundji/Exercises/11. Zorn´s Lemma; Zermelo´s Theorem.md",
            "linksCollapsed": false,
            "unlinkedCollapsed": true
          }
        }
      },
      {
        "id": "56729c9a191b90d1",
        "type": "leaf",
        "state": {
          "type": "outline",
          "state": {
            "file": "Textbooks/Undergraduate/Second Year/Topology Dugundji/Exercises/11. Zorn´s Lemma; Zermelo´s Theorem.md"
          }
        }
      }
    ],
    "currentTab": 0
  },
  "left-ribbon": {
    "hiddenItems": {
      "obsidian-excalidraw-plugin:Create new drawing": false,
      "obsidian-git:Open Git source control": false,
      "switcher:Open quick switcher": false,
      "graph:Open graph view": false,
      "templates:Insert template": false,
      "command-palette:Open command palette": false,
      "table-editor-obsidian:Advanced Tables Toolbar": false,
      "omnisearch:Omnisearch": false
    }
  },
  "active": "e520ba2e4beb7d0a",
  "lastOpenFiles": [
    "Pasted image 20241001155635.png",
    "Pasted image 20241001160342.png",
    "University/Undergraduate/Second Year/Advanced Algebra 1/Lectures/4. Automorphisms and Free Groups.md",
    "University/Undergraduate/Second Year/Advanced Algebra 1/Lectures/3. Group Actions.md",
    "Textbooks/Undergraduate/Second Year/Topology Dugundji/Exercises/10. Orderings.md",
    "Textbooks/Undergraduate/Second Year/Topology Dugundji/Exercises/9. General Cartesian Products.md",
    "Textbooks/Undergraduate/Second Year/Topology Dugundji/Exercises/11. Zorn´s Lemma; Zermelo´s Theorem.md",
    "Textbooks/Undergraduate/Second Year/Topology Dugundji/Topology Dugundji.md",
    "Directory.md",
    "6. Boundary and Interior of a Set.md",
    "University/Undergraduate/Second Year/Real Analysis 1/Homework/Worksheets/real_anal_1.pdf",
    "Untitled",
    "University/Undergraduate/Second Year/Real Analysis 1/Homework/Homework 1.md",
    "University/Undergraduate/Second Year/Real Analysis 1/Real Analysis 1.md",
    "University/Undergraduate/Second Year/Introduction to Number Theory 1/Lectures/2. Linear Diophantine Equations.md",
    "University/Undergraduate/Second Year/Introduction to Number Theory 1/Introduction to Number Theory 1.md",
    "Subjects/Intro to Algebra 1/8. Congruences and Groups.md",
    "Subjects/Intro to Algebra 1/Intro to Algebra 1.md",
    "Subjects/Linear Algebra and Geometry 1/Linear Algebra and Geometry 1.md",
    "Subjects/Linear Algebra and Geometry 1/15..md",
    "Subjects/Linear Algebra and Geometry 1/16. Dimension Theorem and Principle of Linearity.md",
    "Subjects/Linear Algebra and Geometry 1/14. Echelon Form.md",
    "Textbooks/Sequences and Series Lecture Notes.pdf",
    "Subjects/Sequences and Series 1/Sequences and Series 1.md",
    "Homework/LinearAlgGeo1 HW3.pdf",
    "Subjects/Linear Algebra and Geometry 1/Problem sheet 3.md",
    "Subjects/Intro to Algebra 1/Problem Sheet 3.md",
    "Homework/Calculus 1 HW3.pdf",
    "Pasted image 20231017163925.png",
    "Pasted image 20231017164730.png",
    "unit-circle-with-trig.svg",
    "trigonometric-functions.svg",
    "Subjects/Calculus 1/Problem Sheet 3.md",
    "Knowledge/Identities/Trigonometry and Hyperbolic Trigonometry.md",
    "Knowledge/Identities",
    "Knowledge",
    "Subjects/Linear Algebra and Geometry 1/5. Introduction to Vectors.md",
    "Subjects/Calculus 1/Calculus 1.md",
    "Pasted image 20231009134706.png",
    "Pasted image 20231009130903.png",
    "Pasted image 20231009125526.png",
    "Pasted image 20231009125529.png",
    "Pasted image 20231009121430.png",
    "Textbooks/Classic Set Theory For Guided Independent Study - Derek C Goldrei.pdf",
    "Textbooks/Intro to Abstract Algebra lecture notes.pdf",
    "Textbooks/Discrete Mathematics Lecture notes KCL.pdf"
  ]
}